{"type":"FeatureCollection","features":[{"type":"Feature","geometry":{"type":"Point","coordinates":[-73.569415,45.499123]},"properties":{"name":"","description":"","Date":"2016-11-06","Heure_debut":"11:00","Heure_fin":"18:00","Lieu":"Place du Canada","Camion":"Gaufrabec","Truckid":"T00010001"}},{"type":"Feature","geometry":{"type":"Point","coordinates":[-73.569415,45.499123]},"properties":{"name":"","description":"","Date":"2016-11-10","Heure_debut":"11:00","Heure_fin":"18:00","Lieu":"Place du Canada","Camion":"Gaufrabec","Truckid":"T00010001"}},{"type":"Feature","geometry":{"type":"Point","coordinates":[-73.5579,45.504703]},"properties":{"name":"","description":"","Date":"2016-11-11","Heure_debut":"11:00","Heure_fin":"18:00","Lieu":"Place d\u0026#039;Armes","Camion":"Gaufrabec","Truckid":"T00010001"}},{"type":"Feature","geometry":{"type":"Point","coordinates":[-73.569415,45.499123]},"properties":{"name":"","description":"","Date":"2016-11-12","Heure_debut":"11:00","Heure_fin":"18:00","Lieu":"Place du Canada","Camion":"Gaufrabec","Truckid":"T00010001"}},{"type":"Feature","geometry":{"type":"Point","coordinates":[-73.5579,45.504703]},"properties":{"name":"","description":"","Date":"2016-11-13","Heure_debut":"11:00","Heure_fin":"18:00","Lieu":"Place d\u0026#039;Armes","Camion":"Gaufrabec","Truckid":"T00010001"}},{"type":"Feature","geometry":{"type":"Point","coordinates":[-73.5579,45.504703]},"properties":{"name":"","description":"","Date":"2016-11-17","Heure_debut":"11:00","Heure_fin":"18:00","Lieu":"Place d\u0026#039;Armes","Camion":"Gaufrabec","Truckid":"T00010001"}},{"type":"Feature","geometry":{"type":"Point","coordinates":[-73.569415,45.499123]},"properties":{"name":"","description":"","Date":"2016-11-18","Heure_debut":"11:00","Heure_fin":"18:00","Lieu":"Place du Canada","Camion":"Gaufrabec","Truckid":"T00010001"}},{"type":"Feature","geometry":{"type":"Point","coordinates":[-73.5579,45.504703]},"properties":{"name":"","description":"","Date":"2016-11-19","Heure_debut":"11:00","Heure_fin":"18:00","Lieu":"Place d\u0026#039;Armes","Camion":"Gaufrabec","Truckid":"T00010001"}},{"type":"Feature","geometry":{"type":"Point","coordinates":[-73.569415,45.499123]},"properties":{"name":"","description":"","Date":"2016-11-20","Heure_debut":"11:00","Heure_fin":"18:00","Lieu":"Place du Canada","Camion":"Gaufrabec","Truckid":"T00010001"}}]}